mafw_tools/__about__.py
mafw_tools/__init__.py
mafw_tools/file_tools.py
mafw_tools/generic_tools.py
mafw_tools/plotting_tools.py
mafw_tools-1.0.0.dist-info/METADATA
mafw_tools-1.0.0.dist-info/WHEEL
mafw_tools-1.0.0.dist-info/licenses/LICENSE.txt
mafw_tools-1.0.0.dist-info/RECORD
