Metadata-Version: 2.4
Name: mafw-tools
Version: 1.0.0
Summary: A set of commonly used tools to be used with MAFw and others
Project-URL: Documentation, https://gitlab.jrc.ec.europa.eu/jrc-projects/autorad/mafw-tools
Project-URL: Issues, https://gitlab.jrc.ec.europa.eu/jrc-projects/autorad/mafw-tools/-/issues
Project-URL: Source, https://gitlab.jrc.ec.europa.eu/jrc-projects/autorad/mafw-tools
Author-email: BULGHERONI Antonio <Antonio.BULGHERONI@ec.europa.eu>
License-Expression: EUPL-1.2
License-File: LICENSE.txt
Keywords: data-analysis
Classifier: Development Status :: 4 - Beta
Classifier: Intended Audience :: Science/Research
Classifier: Operating System :: OS Independent
Classifier: Programming Language :: Python
Classifier: Programming Language :: Python :: 3.12
Classifier: Programming Language :: Python :: Implementation :: CPython
Classifier: Topic :: Scientific/Engineering
Requires-Python: >=3.8
Requires-Dist: matplotlib
Provides-Extra: dev
Requires-Dist: pre-commit; extra == 'dev'
Requires-Dist: ruff; extra == 'dev'
Provides-Extra: test
Requires-Dist: pre-commit; extra == 'test'
Requires-Dist: pytest; extra == 'test'
Requires-Dist: ruff; extra == 'test'
